{
  "project_info": {
    "project_number": "962346468274",
    "project_id": "inkup-c930e",
    "storage_bucket": "inkup-c930e.firebasestorage.app"
  },
  "client": [
    {
      "client_info": {
        "mobilesdk_app_id": "1:962346468274:android:a65876b3e5177b73e41aab",
        "android_client_info": {
          "package_name": "com.example.inkup_mvp"
        }
      },
      "oauth_client": [],
      "api_key": [
        {
          "current_key": "AIzaSyAzVF1_VyB8CFHTZvbsQN_Tg6JMQimCIec"
        }
      ],
      "services": {
        "appinvite_service": {
          "other_platform_oauth_client": []
        }
      }
    }
  ],
  "configuration_version": "1"
}